{"skeleton":{"hash":"ovcJbKGNiZYspfq0Bl6Zl1G3uwg","spine":"3.8.69","x":-750,"y":1.08,"width":1500,"height":650,"images":"./images/","audio":""},"bones":[{"name":"root"},{"name":"EP04_2_1_00000","parent":"root","y":326.08}],"slots":[{"name":"EP04_2_1_00000","bone":"EP04_2_1_00000","attachment":"EP04_2_1_00000"}],"skins":[{"name":"default","attachments":{"EP04_2_1_00000":{"EP04_2_1_00000":{"width":1500,"height":650},"EP04_2_1_00001":{"width":1500,"height":650},"EP04_2_1_00002":{"width":1500,"height":650},"EP04_2_1_00003":{"width":1500,"height":650},"EP04_2_1_00004":{"width":1500,"height":650},"EP04_2_1_00005":{"width":1500,"height":650},"EP04_2_1_00006":{"width":1500,"height":650},"EP04_2_1_00007":{"width":1500,"height":650},"EP04_2_1_00008":{"width":1500,"height":650},"EP04_2_1_00009":{"width":1500,"height":650},"EP04_2_1_00010":{"width":1500,"height":650},"EP04_2_2_00022":{"width":1500,"height":650},"EP04_2_2_00023":{"width":1500,"height":650},"EP04_2_2_00024":{"width":1500,"height":650},"EP04_2_2_00025":{"width":1500,"height":650},"EP04_2_2_00026":{"width":1500,"height":650},"EP04_2_2_00027":{"width":1500,"height":650},"EP04_2_2_00028":{"width":1500,"height":650},"EP04_2_2_00029":{"width":1500,"height":650},"EP04_2_2_00030":{"width":1500,"height":650},"EP04_2_2_00031":{"width":1500,"height":650},"EP04_2_2_00032":{"width":1500,"height":650},"EP04_2_2_00033":{"width":1500,"height":650},"EP04_2_2_00034":{"width":1500,"height":650},"EP04_2_2_00035":{"width":1500,"height":650},"EP04_2_2_00036":{"width":1500,"height":650},"EP04_2_2_00037":{"width":1500,"height":650},"EP04_2_2_00038":{"width":1500,"height":650},"EP04_2_2_00039":{"width":1500,"height":650},"EP04_2_2_00040":{"width":1500,"height":650},"EP04_2_2_00041":{"width":1500,"height":650},"EP04_2_2_00042":{"width":1500,"height":650},"EP04_2_2_00043":{"width":1500,"height":650},"EP04_2_2_00044":{"width":1500,"height":650},"EP04_2_2_00045":{"width":1500,"height":650},"EP04_2_2_00046":{"width":1500,"height":650},"EP04_2_2_00047":{"width":1500,"height":650},"EP04_2_2_00048":{"width":1500,"height":650},"EP04_2_2_00049":{"width":1500,"height":650},"EP04_2_2_00050":{"width":1500,"height":650},"EP04_2_2_00051":{"width":1500,"height":650},"EP04_2_2_00052":{"width":1500,"height":650},"EP04_2_2_00053":{"width":1500,"height":650},"EP04_2_2_00054":{"width":1500,"height":650},"EP04_2_2_00055":{"width":1500,"height":650},"EP04_2_2_00056":{"width":1500,"height":650},"EP04_2_2_00057":{"width":1500,"height":650}}}}],"animations":{"dzy_zhua1":{"slots":{"EP04_2_1_00000":{"attachment":[{"name":"EP04_2_1_00000"},{"time":0.0667,"name":"EP04_2_1_00001"},{"time":0.1333,"name":"EP04_2_1_00002"},{"time":0.2,"name":"EP04_2_1_00003"},{"time":0.2667,"name":"EP04_2_1_00004"},{"time":0.3333,"name":"EP04_2_1_00005"},{"time":0.4,"name":"EP04_2_1_00006"},{"time":0.4667,"name":"EP04_2_1_00007"},{"time":0.5333,"name":"EP04_2_1_00008"},{"time":0.6,"name":"EP04_2_1_00009"},{"time":0.6667,"name":"EP04_2_1_00010"},{"time":0.7333,"name":"EP04_2_1_00010"},{"time":0.8,"name":"EP04_2_1_00009"},{"time":0.8667,"name":"EP04_2_1_00008"},{"time":0.9333,"name":"EP04_2_1_00007"},{"time":1,"name":"EP04_2_1_00006"},{"time":1.0667,"name":"EP04_2_1_00005"},{"time":1.1333,"name":"EP04_2_1_00004"},{"time":1.2,"name":"EP04_2_1_00003"},{"time":1.2667,"name":"EP04_2_1_00002"},{"time":1.3333,"name":"EP04_2_1_00001"},{"time":1.4,"name":"EP04_2_1_00000"}]}},"bones":{"EP04_2_1_00000":{"rotate":[{}],"translate":[{}],"scale":[{}]}}},"dzy_zhua2":{"slots":{"EP04_2_1_00000":{"attachment":[{"name":"EP04_2_2_00022"},{"time":0.0667,"name":"EP04_2_2_00023"},{"time":0.1333,"name":"EP04_2_2_00024"},{"time":0.2,"name":"EP04_2_2_00025"},{"time":0.2667,"name":"EP04_2_2_00026"},{"time":0.3333,"name":"EP04_2_2_00027"},{"time":0.4,"name":"EP04_2_2_00028"},{"time":0.4667,"name":"EP04_2_2_00029"},{"time":0.5333,"name":"EP04_2_2_00030"},{"time":0.6,"name":"EP04_2_2_00031"},{"time":0.6667,"name":"EP04_2_2_00032"},{"time":0.7333,"name":"EP04_2_2_00033"},{"time":0.8,"name":"EP04_2_2_00034"},{"time":0.8667,"name":"EP04_2_2_00035"},{"time":0.9333,"name":"EP04_2_2_00036"},{"time":1,"name":"EP04_2_2_00037"},{"time":1.0667,"name":"EP04_2_2_00038"},{"time":1.1333,"name":"EP04_2_2_00039"},{"time":1.2,"name":"EP04_2_2_00040"},{"time":1.2667,"name":"EP04_2_2_00041"},{"time":1.3333,"name":"EP04_2_2_00042"},{"time":1.4,"name":"EP04_2_2_00043"},{"time":1.4667,"name":"EP04_2_2_00044"},{"time":1.5333,"name":"EP04_2_2_00045"},{"time":1.6,"name":"EP04_2_2_00046"},{"time":1.6667,"name":"EP04_2_2_00047"},{"time":1.7333,"name":"EP04_2_2_00048"},{"time":1.8,"name":"EP04_2_2_00049"},{"time":1.8667,"name":"EP04_2_2_00050"},{"time":1.9333,"name":"EP04_2_2_00051"},{"time":2,"name":"EP04_2_2_00052"},{"time":2.0667,"name":"EP04_2_2_00053"},{"time":2.1333,"name":"EP04_2_2_00054"},{"time":2.2,"name":"EP04_2_2_00055"},{"time":2.2667,"name":"EP04_2_2_00056"},{"time":2.3333,"name":"EP04_2_2_00057"},{"time":2.4,"name":"EP04_2_2_00022"}]}},"bones":{"EP04_2_1_00000":{"rotate":[{}],"translate":[{}],"scale":[{}]}}}}}